v_program5/__init__.py
v_program5/__main__.py
v_program5/cli.py
v_program5/ml_model.py
v_program5/test.py
v_program5-0.1.5.dist-info/METADATA
v_program5-0.1.5.dist-info/WHEEL
v_program5-0.1.5.dist-info/entry_points.txt
v_program5-0.1.5.dist-info/top_level.txt
v_program5-0.1.5.dist-info/RECORD
